LICENSE
README.md
setup.cfg
setup.py
StockInsider.egg-info/PKG-INFO
StockInsider.egg-info/SOURCES.txt
StockInsider.egg-info/dependency_links.txt
StockInsider.egg-info/requires.txt
StockInsider.egg-info/top_level.txt
insider/__init__.py
insider/constants.py
insider/stock.py
insider/stock_insider.py
insider/utils.py
insider/indicators/__init__.py
insider/indicators/base.py
insider/indicators/price.py
insider/indicators/sar.py
insider/indicators/volume.py