Metadata-Version: 2.1
Name: StockInsider
Version: 0.2.0
Summary: The Python implementation of an stock analysis and visualization tool.
Home-page: https://github.com/charlesdong1991/StockInsider
Author: Kaiqi Dong
Author-email: kaiqidong1991@gmail.com
License: UNKNOWN
Keywords: stock,visualization,insight,stock analysis,python,finance
Platform: UNKNOWN
Classifier: Development Status :: 3 - Alpha
Classifier: License :: OSI Approved :: MIT License
Classifier: Programming Language :: Python :: 3.6
Classifier: Programming Language :: Python :: 3.7
Classifier: Topic :: Software Development :: Libraries
